shapefile.py
ironpyshp-2.3.2.dist-info/licenses/LICENSE.TXT
ironpyshp-2.3.2.dist-info/METADATA
ironpyshp-2.3.2.dist-info/WHEEL
ironpyshp-2.3.2.dist-info/top_level.txt
ironpyshp-2.3.2.dist-info/RECORD
