Metadata-Version: 2.4
Name: IronPyshp
Version: 2.3.2
Summary: Pure Python read/write support for ESRI Shapefile format
Home-page: https://github.com/JamesParrott/IronPyShp
Download-URL: https://pypi.org/project/IronPyShp
Author: Joel Lawhead
Author-email: jlawhead@geospatialpython.com
Maintainer: James Parrott
Maintainer-email: james.parrott@proton.me
License: MIT
Keywords: gis,geospatial,geographic,shapefile,shapefiles
Classifier: Development Status :: 5 - Production/Stable
Classifier: Programming Language :: Python
Classifier: Programming Language :: Python :: 2.7
Classifier: Programming Language :: Python :: 3
Classifier: Topic :: Scientific/Engineering :: GIS
Classifier: Topic :: Software Development :: Libraries
Classifier: Topic :: Software Development :: Libraries :: Python Modules
Requires-Python: >=2.7
License-File: LICENSE.TXT
Dynamic: download-url
Dynamic: license-file
